observable_jupyter/__init__.py
observable_jupyter/iframe_bundle.js
observable_jupyter/jupyter_embed.py
observable_jupyter/logo.svg
observable_jupyter/wrapper_bundle.js
observable_jupyter-0.1.14.dist-info/LICENSE
observable_jupyter-0.1.14.dist-info/METADATA
observable_jupyter-0.1.14.dist-info/WHEEL
observable_jupyter-0.1.14.dist-info/top_level.txt
observable_jupyter-0.1.14.dist-info/RECORD
