Metadata-Version: 2.1
Name: observable-jupyter
Version: 0.1.14
Summary: Embed Observable cells hosted on observablehq.com into Jupyter notebooks.
Home-page: https://github.com/observablehq/observable_jupyter
Author: Thomas Ballinger
Author-email: me@ballingt.com
License: ISC license
Keywords: observable_jupyter
Classifier: Development Status :: 2 - Pre-Alpha
Classifier: License :: OSI Approved :: ISC License (ISCL)
Classifier: Natural Language :: English
Classifier: Programming Language :: Python :: 3
Requires-Python: >=3.6
License-File: LICENSE
Provides-Extra: dev
Requires-Dist: jupyter ; extra == 'dev'
Requires-Dist: nox ; extra == 'dev'
Requires-Dist: pytest ; extra == 'dev'
Provides-Extra: test
Requires-Dist: pytest ; extra == 'test'
Requires-Dist: IPython ; extra == 'test'
